bonsai_classifications-0.4.19.dist-info/licenses/LICENSE.txt
classifications/__init__.py
classifications/_level.py
classifications/_mapping_type.py
classifications/_pint_units.py
classifications/_utils.py
classifications/core.py
classifications/disaggregate_bonsai.py
classifications/merge_bonsai_concordances.py
classifications/data/__init__.py
classifications/data/dataquality/dim_bonsai_v2_0.csv
classifications/data/dataquality/resources.csv
classifications/data/flow/bonsai_v2_0_sut_products_from_industries.csv
classifications/data/flow/bonsai_v2_0_sut_products_to_markets.csv
classifications/data/flow/conc_adb_supplier_bonsai_v2_0.csv
classifications/data/flow/conc_adb_user_bonsai_v2_0.csv
classifications/data/flow/concpair_bonsai_v2_0_iea_energy_balance.csv
classifications/data/flow/concpair_bonsai_v2_0_statcan_chemicals.csv
classifications/data/flow/concpair_bonsai_v2_0_undata_energy_stats.csv
classifications/data/flow/resources.csv
classifications/data/flow/tree_adb_supplier.csv
classifications/data/flow/tree_adb_user.csv
classifications/data/flow/activitytype/conc_bea_activ_bonsai_v2_0.csv
classifications/data/flow/activitytype/conc_bonsut_v2_0_bonsai_v2_0.csv
classifications/data/flow/activitytype/conc_bonsut_v2_0_hexio_v_3_3_18.csv
classifications/data/flow/activitytype/conc_ec_2008_98_nace_rev2.csv
classifications/data/flow/activitytype/conc_isic_africa_bonsai_v2_0.csv
classifications/data/flow/activitytype/conc_isic_rev4_bonsai_v2_0.csv
classifications/data/flow/activitytype/conc_isic_rev4_nace_rev2.csv
classifications/data/flow/activitytype/conc_japan_activ_bonsai_v2_0.csv
classifications/data/flow/activitytype/conc_nace_rev2_bonsai_v2_0.csv
classifications/data/flow/activitytype/dim_ec_2008_98.csv
classifications/data/flow/activitytype/dim_level.csv
classifications/data/flow/activitytype/resources.csv
classifications/data/flow/activitytype/tree_bea_activ.csv
classifications/data/flow/activitytype/tree_bonsai_v2_0.csv
classifications/data/flow/activitytype/tree_bonsut_v2_0.csv
bonsai_classifications-0.4.19.dist-info/METADATA
bonsai_classifications-0.4.19.dist-info/WHEEL
bonsai_classifications-0.4.19.dist-info/top_level.txt
bonsai_classifications-0.4.19.dist-info/RECORD
