Metadata-Version: 2.4
Name: bonsai_classifications
Version: 0.4.19
Summary: "Python package classifications of the util workflow stage of the BONSAI database"
Home-page: https://gitlab.com/bonsamurais/bonsai/util/classifications
Author: admin_bonsai
Author-email: admin.gettingthedataright@aau.dk
License: MIT
Project-URL: Documentation, http://bonsamurais.gitlab.io/bonsai/util/classifications
Platform: any
Classifier: Development Status :: 4 - Beta
Classifier: Programming Language :: Python
License-File: LICENSE.txt
Requires-Dist: importlib-metadata
Requires-Dist: pandas
Requires-Dist: pyyaml
Requires-Dist: pint
Requires-Dist: anytree
Provides-Extra: testing
Requires-Dist: setuptools>=65.6.3; extra == "testing"
Requires-Dist: pytest>=7.2.2; extra == "testing"
Requires-Dist: pytest-cov>=4.0.0; extra == "testing"
Requires-Dist: importlib_resources; extra == "testing"
Requires-Dist: anytree; extra == "testing"
Dynamic: license-file
